entrel/__init__.py
entrel/__main__.py
entrel-0.1.1.dist-info/LICENSE
entrel-0.1.1.dist-info/METADATA
entrel-0.1.1.dist-info/WHEEL
entrel-0.1.1.dist-info/RECORD
