Metadata-Version: 2.3
Name: entrel
Version: 0.1.1
Summary: Generate simple Entity Relationship diagrams in LaTeX from TOML files.
Author: Inti
Author-email: intimyp@gmail.com
Requires-Python: >=3.11
Classifier: Intended Audience :: Developers
Classifier: License :: OSI Approved :: MIT License
Classifier: Programming Language :: Python :: 3
Classifier: Programming Language :: Python
Classifier: Topic :: Software Development :: Libraries
Project-URL: Changelog, https://github.com/imyp/entrel/releases
Project-URL: Homepage, https://github.com/imyp/entrel
Project-URL: Issues, https://github.com/imyp/entrel/issues
Project-URL: Repository, https://github.com/imyp/entrel
